{
  "project_info": {
    "project_number": "92715725077",
    "project_id": "find-a-doctor-23b9d",
    "storage_bucket": "find-a-doctor-23b9d.appspot.com"
  },
  "client": [
    {
      "client_info": {
        "mobilesdk_app_id": "1:92715725077:android:2d0c259d4b2e374079b91c",
        "android_client_info": {
          "package_name": "com.example.find_a_doctor"
        }
      },
      "oauth_client": [],
      "api_key": [
        {
          "current_key": "AIzaSyCC2fydzaR5pSzM3vvPCdpVqM5y98pEqxs"
        }
      ],
      "services": {
        "appinvite_service": {
          "other_platform_oauth_client": []
        }
      }
    }
  ],
  "configuration_version": "1"
}